README.rst
setup.py
PathCORE_T.egg-info/PKG-INFO
PathCORE_T.egg-info/SOURCES.txt
PathCORE_T.egg-info/dependency_links.txt
PathCORE_T.egg-info/requires.txt
PathCORE_T.egg-info/top_level.txt
pathcore/__init__.py
pathcore/feature_pathway_overrepresentation.py
pathcore/network.py
pathcore/network_permutation_test.py