Metadata-Version: 1.1
Name: PathCORE-T
Version: 1.0.2
Summary: Python 3 implementation of PathCORE-T analysis methods
Home-page: https://github.com/greenelab/PathCORE-T
Author: Greene Lab
Author-email: team@greenelab.com
License: BSD-3-Clause
Platform: UNKNOWN
Classifier: Intended Audience :: Developers
Classifier: License :: OSI Approved :: BSD License
Classifier: Operating System :: OS Independent
Classifier: Programming Language :: Python
Classifier: Programming Language :: Python :: 3
Classifier: Topic :: Scientific/Engineering :: Bio-Informatics
